xarray_well_ice/__init__.py
xarray_well_ice/xw_load.py
xarray_well_ice/xw_pressure.py
xarray_well_ice/xw_tilt.py
xarray_well_ice-0.1.10.dist-info/LICENSE
xarray_well_ice-0.1.10.dist-info/METADATA
xarray_well_ice-0.1.10.dist-info/WHEEL
xarray_well_ice-0.1.10.dist-info/RECORD
