Metadata-Version: 2.1
Name: xarray-well-ice
Version: 0.1.10
Summary: A package to process pressure and tilt borehole data
Home-page: https://xarray-well-ice-mecaiceige-tools-lib-python-a1d7b6168ff878b45d0.gricad-pages.univ-grenoble-alpes.fr/
License: GPLv3
Keywords: xarray
Author: Thomas Chauve
Author-email: thomas.chauve@univ-grenoble-alpes.fr
Requires-Python: >=3.10,<4.0
Classifier: License :: Other/Proprietary License
Classifier: Programming Language :: Python :: 3
Classifier: Programming Language :: Python :: 3.10
Classifier: Programming Language :: Python :: 3.11
Classifier: Programming Language :: Python :: 3.12
Provides-Extra: docs
Requires-Dist: Sphinx (>=7.4.0,<8.0.0) ; extra == "docs"
Requires-Dist: matplotlib (>=3.9.0,<4.0.0)
Requires-Dist: nbsphinx (>=0.9.3,<0.10.0) ; extra == "docs"
Requires-Dist: pandas (>=2.2.2,<3.0.0)
Requires-Dist: pandoc (>=2.4,<3.0) ; extra == "docs"
Requires-Dist: python-docs-theme (>=2024.6,<2025.0) ; extra == "docs"
Requires-Dist: sphinx-rtd-theme (>=2.0.0,<3.0.0) ; extra == "docs"
Requires-Dist: twine (>=5.1.1,<6.0.0) ; extra == "docs"
Requires-Dist: xarray (>=2024.7.0,<2025.0.0)
Project-URL: Repository, https://gricad-gitlab.univ-grenoble-alpes.fr/mecaiceige/tools/lib_python/xarray_well_ice
